MANIFEST.in
README.md
setup.cfg
setup.py
django_smart_selects_fix.egg-info/PKG-INFO
django_smart_selects_fix.egg-info/SOURCES.txt
django_smart_selects_fix.egg-info/dependency_links.txt
django_smart_selects_fix.egg-info/top_level.txt
smart_selects/__init__.py
smart_selects/db_fields.py
smart_selects/form_fields.py
smart_selects/models.py
smart_selects/tests.py
smart_selects/urls.py
smart_selects/utils.py
smart_selects/views.py
smart_selects/widgets.py
smart_selects/static/smart-selects/admin/js/bindfields.js
smart_selects/static/smart-selects/admin/js/chainedfk.js
smart_selects/static/smart-selects/admin/js/chainedm2m.js