Metadata-Version: 2.1
Name: django-smart-selects-fix
Version: 1.0
Summary: Django application to handle chained model fields.
Home-page: https://github.com/Murakam1/smart-select-novo
Author: Patrick Lauber
Author-email: digi@treepy.com
License: UNKNOWN
Platform: UNKNOWN
Classifier: Programming Language :: Python :: 2
Classifier: Programming Language :: Python :: 3
